waypoint_api/__init__.py
waypoint_api/auth_flow.py
waypoint_api/waypoint.py
waypoint_api/endpoints/h5.json
waypoint_api/endpoints/hi.json
waypoint_api-1.0.13.dist-info/METADATA
waypoint_api-1.0.13.dist-info/WHEEL
waypoint_api-1.0.13.dist-info/top_level.txt
waypoint_api-1.0.13.dist-info/RECORD
